setup.py
dsnd_distributions_prob/Binomialdistribution.py
dsnd_distributions_prob/Gaussiandistribution.py
dsnd_distributions_prob/Generaldistribution.py
dsnd_distributions_prob/__init__.py
dsnd_distributions_prob.egg-info/PKG-INFO
dsnd_distributions_prob.egg-info/SOURCES.txt
dsnd_distributions_prob.egg-info/dependency_links.txt
dsnd_distributions_prob.egg-info/not-zip-safe
dsnd_distributions_prob.egg-info/top_level.txt