Metadata-Version: 1.0
Name: dsnd-distributions-prob
Version: 0.1
Summary: Gaussian and Binomial distributions
Home-page: UNKNOWN
Author: Saumya Garg
Author-email: saumyagarg2299@gmail.com
License: UNKNOWN
Platform: UNKNOWN
